betterproto2/__init__.py
betterproto2/_types.py
betterproto2/_version.py
betterproto2/casing.py
betterproto2/enum_.py
betterproto2/message_pool.py
betterproto2/py.typed
betterproto2/utils.py
betterproto2/grpclib/__init__.py
betterproto2/grpclib/grpclib_client.py
betterproto2/grpclib/grpclib_server.py
betterproto2/validators/__init__.py
betterproto2/validators/proto_types.py
betterproto2-0.9.0.dist-info/METADATA
betterproto2-0.9.0.dist-info/WHEEL
betterproto2-0.9.0.dist-info/RECORD
